{
  "sessions": {
    "1": {
      "speakers": ["celineLouvet"],
      "tags": [],
      "title": "Les mystères des permissions",
      "id": "1",
      "startTime": "2023-06-20T15:00:00+02:00",
      "endTime": "2023-06-20T16:00:00+02:00",
      "trackTitle": "Salle 1"
    }
  },
  "speakers": {
    "celineLouvet": {
      "name": "Céline LOUVET",
      "photoUrl": "https://lh5.googleusercontent.com/-NV7T8s_7MLE/AAAAAAAAAAI/AAAAAAAAMUk/RxKDadfzuV8/photo.jpg",
      "socials": [
        {
          "name": "twitter",
          "link": "https://twitter.com/celine_louvet"
        },
        {
          "name": "LinkedIn",
          "link": "https://www.linkedin.com/in/celinelouvet"
        },
        {
          "name": "Mastodon",
          "link": "https://pouet.chapril.org/@celine_louvet"
        }
      ],
      "id": "celineLouvet"
    }
  }
}
